anime/__init__.py
anime/core/anime.py
anime/core/filter.py
anime/core/freezeband.py
anime/core/pipe.py
anime/core/reducer.py
anime/core/renderer.py
anime/core/rubberband.py
anime/core/__init__.py
anime/demo/demo1.py
anime/demo/demo2.py
anime/demo/demo3.py
anime/demo/demo4.py
anime/demo/demo5.py
anime/demo/demo6.py
anime/demo/demo7.py
anime/demo/demo8.py
anime/demo/__init__.py
anime/demo/images/image1.png
anime/math/bezier.py
anime/math/parametric.py
anime/math/polar.py
anime/math/__init__.py
anime/tests/filter_test.py
anime/tests/freezeband_test.py
anime/tests/pipe_test.py
anime/tests/rubberband_test.py
anime/tests/__init__.py
anime-1.1.0.dist-info/DESCRIPTION.rst
anime-1.1.0.dist-info/METADATA
anime-1.1.0.dist-info/metadata.json
anime-1.1.0.dist-info/RECORD
anime-1.1.0.dist-info/top_level.txt
anime-1.1.0.dist-info/WHEEL
