Metadata-Version: 2.0
Name: anime
Version: 1.1.0
Summary: Declarative animation library for pygame.
Home-page: https://github.com/SodaCookie/anime
Author: Eric Zhang
Author-email: eric.quin.zhang@gmail.com
License: MIT
Keywords: pygame animation anime
Platform: UNKNOWN
Classifier: Development Status :: 4 - Beta
Classifier: Intended Audience :: Developers
Classifier: Topic :: Software Development :: Libraries :: pygame
Classifier: License :: OSI Approved :: MIT License
Classifier: Programming Language :: Python :: 3.2
Requires-Dist: pygame
